bedshift/BedshiftYAMLHandler.py
bedshift/__init__.py
bedshift/_version.py
bedshift/arguments.py
bedshift/bedshift.py
bedshift-1.1.1.dist-info/LICENSE.txt
bedshift-1.1.1.dist-info/METADATA
bedshift-1.1.1.dist-info/WHEEL
bedshift-1.1.1.dist-info/entry_points.txt
bedshift-1.1.1.dist-info/top_level.txt
bedshift-1.1.1.dist-info/RECORD
