Metadata-Version: 2.1
Name: bedshift
Version: 1.1.1
Summary: BED file perturbations
Home-page: https://bedshift.databio.org
Author: Aaron Gu
Author-email: ag5ym@virginia.edu
License: BSD2
Keywords: BED file,perturbation,bioinformatics,region set
Platform: UNKNOWN
Classifier: Development Status :: 4 - Beta
Classifier: License :: OSI Approved :: BSD License
Classifier: Programming Language :: Python :: 3.5
Classifier: Programming Language :: Python :: 3.6
Classifier: Topic :: System :: Distributed Computing
Requires-Dist: logmuse
Requires-Dist: pandas
Requires-Dist: numpy
Requires-Dist: pyranges
